alca/__init__.py
alca-0.0.0.dist-info/METADATA
alca-0.0.0.dist-info/WHEEL
alca-0.0.0.dist-info/top_level.txt
alca-0.0.0.dist-info/RECORD
