Metadata-Version: 2.1
Name: alca
Version: 0.0.0
Summary: Coming soon
Author-email: Dion Jakobs <dion.jakobs@chem.ethz.ch>, Maximilian Hoepfner <maximilian.hoepfner@chem.ethz.ch>
